{
    "quizzes": [
        {
            "question": "1. 코디세이 미션에서 강조하는, 프로그래밍 언어를 배우는 가장 확실한 방법은 무엇일까요?",
            "choices": [
                "문법 달달 외우기",
                "동작하는 프로그램을 처음부터 끝까지 직접 만들기",
                "유명한 강의 반복해서 보기",
                "남이 짠 코드 복사하기"
            ],
            "answer": 2
        },
        {
            "question": "2. 미션 2에서 퀴즈 문제들을 쉽게 찍어내기 위해 우리가 만든 '붕어빵 틀'의 파이썬 문법 이름은 무엇일까요?",
            "choices": [
                "변수(Variable)",
                "함수(Function)",
                "클래스(Class)",
                "리스트(List)"
            ],
            "answer": 3
        },
        {
            "question": "3. 프로그램을 껐다 켜도 솔바오의 퀴즈 데이터와 점수가 날아가지 않게 보존해 주는 파일의 확장자는?",
            "choices": [
                ".txt",
                ".pdf",
                ".json",
                ".png"
            ],
            "answer": 3
        },
        {
            "question": "4. 방금 전 로컬(내 컴퓨터)에 있는 파일들을 인터넷(GitHub)으로 쏘아 올릴 때 사용했던 마법의 명령어는?",
            "choices": [
                "git clone",
                "git add",
                "git commit",
                "git push"
            ],
            "answer": 4
        },
        {
            "question": "5. 우리가 GitHub에 첫 집터(저장소)를 만들 때, 충돌 에러를 막기 위해 절대 체크하지 않았던 것은?",
            "choices": [
                "Public 설정",
                "Repository name",
                "Add a README file",
                "Create 버튼"
            ],
            "answer": 3
        },
        {
            "question": "Python에서 까만 화면(터미널)에 글자를 띄워주는 마법의 단어(함수)는 무엇일까요?",
            "choices": [
                "input",
                "print",
                "class",
                "def"
            ],
            "answer": 2
        },
        {
            "question": "파이썬은 줄 맨 앞의 띄어쓰기에 엄청 예민하다. 파이썬 코드를 복사해서 붙여넣기 할 때 개발자라면 한번쯤 겪는 통과의례 같은 에러는?",
            "choices": [
                "SyntaxError (문법 에러)",
                "NameError (이름 에러)",
                "IndentationError (들여쓰기 에러)",
                "TypeError (타입 에러)"
            ],
            "answer": 3
        },
        {
            "question": "코디세이 교육장에 없는 층은?",
            "choices": [
                "B1",
                "1층",
                "10층",
                "5층"
            ],
            "answer": 3
        }
    ],
    "best_score": 8
}